dagather/__init__.py
dagather/_version.py
dagather/exceptions.py
dagather/multigather.py
dagather/result.py
dagather/sibling_tasks.py
dagather/tasktemplate.py
dagather/util.py
dagather-0.1.0.dist-info/LICENSE
dagather-0.1.0.dist-info/WHEEL
dagather-0.1.0.dist-info/METADATA
dagather-0.1.0.dist-info/RECORD
