Metadata-Version: 2.1
Name: dagather
Version: 0.1.0
Summary: directed acyclic gather
Home-page: https://github.com/bentheiii/dagather
License: MIT lisence
Author: ben avrahami
Requires-Python: >=3.7,<4.0
Classifier: License :: Other/Proprietary License
Classifier: Programming Language :: Python :: 3
Classifier: Programming Language :: Python :: 3.7
Classifier: Programming Language :: Python :: 3.8
Classifier: Programming Language :: Python :: 3.9
Project-URL: Repository, https://github.com/bentheiii/dagather
